charcountpy/__init__.py
charcountpy/collect_framework.py
charcountpy-1.0.0.dist-info/LICENSE.txt
charcountpy-1.0.0.dist-info/METADATA
charcountpy-1.0.0.dist-info/WHEEL
charcountpy-1.0.0.dist-info/top_level.txt
charcountpy-1.0.0.dist-info/RECORD
