Metadata-Version: 2.1
Name: charcountpy
Version: 1.0.0
Summary: A Python package for counting single characters in given string
Author: Mykola Karandiei
Author-email: korondei@gmail.com
Classifier: Programming Language :: Python :: 3
Classifier: License :: OSI Approved :: MIT License
Classifier: Operating System :: OS Independent
License-File: LICENSE.txt
Requires-Dist: argparse
